carbonplan/__init__.py
carbonplan/data.py
carbonplan/forests_offsets.py
carbonplan/forests_risks.py
carbonplan/styles.py
carbonplan/trace.py
carbonplan/watermark.py
carbonplan/tests/test_metapackage.py
carbonplan/tests/test_watermark.py
carbonplan-0.6.0.dist-info/LICENSE
carbonplan-0.6.0.dist-info/METADATA
carbonplan-0.6.0.dist-info/WHEEL
carbonplan-0.6.0.dist-info/top_level.txt
carbonplan-0.6.0.dist-info/RECORD
