Metadata-Version: 2.1
Name: carbonplan
Version: 0.6.0
Summary: CarbonPlan namespace package
Author-email: CarbonPlan <tech@carbonplan.org>
License: MIT
Project-URL: repository, https://github.com/carbonplan/carbonplan-python
Classifier: Development Status :: 2 - Pre-Alpha
Classifier: License :: OSI Approved :: MIT License
Classifier: Operating System :: OS Independent
Classifier: Intended Audience :: Science/Research
Classifier: Programming Language :: Python
Classifier: Programming Language :: Python :: 3
Classifier: Programming Language :: Python :: 3.9
Classifier: Programming Language :: Python :: 3.10
Classifier: Programming Language :: Python :: 3.11
Classifier: Programming Language :: Python :: 3.12
Classifier: Topic :: Scientific/Engineering
Requires-Python: >=3.9
License-File: LICENSE
Requires-Dist: watermark
Provides-Extra: all
Requires-Dist: carbonplan-data ; extra == 'all'
Requires-Dist: carbonplan-styles ; extra == 'all'
Requires-Dist: carbonplan-forest-offsets ; extra == 'all'
Requires-Dist: carbonplan-forest-risks ; extra == 'all'
Provides-Extra: data
Requires-Dist: carbonplan-data ; extra == 'data'
Provides-Extra: dev
Requires-Dist: pytest ; extra == 'dev'
Requires-Dist: carbonplan-data ; extra == 'dev'
Requires-Dist: carbonplan-styles ; extra == 'dev'
Provides-Extra: forest-offsets
Requires-Dist: carbonplan-forest-offsets ; extra == 'forest-offsets'
Provides-Extra: forest-risks
Requires-Dist: carbonplan-forest-risks ; extra == 'forest-risks'
Provides-Extra: styles
Requires-Dist: carbonplan-styles ; extra == 'styles'
